cardpointe/__init__.py
cardpointe/client.py
cardpointe/credentials.py
cardpointe/exceptions.py
cardpointe/utils.py
cardpointe/cardsecure/__init__.py
cardpointe/cardsecure/api.py
cardpointe/cardsecure/resources.py
cardpointe/gateway/__init__.py
cardpointe/gateway/api.py
cardpointe/gateway/constants.py
cardpointe/gateway/resources.py
cardpointe_api_python_client-0.0.2.dist-info/LICENSE
cardpointe_api_python_client-0.0.2.dist-info/METADATA
cardpointe_api_python_client-0.0.2.dist-info/WHEEL
cardpointe_api_python_client-0.0.2.dist-info/top_level.txt
cardpointe_api_python_client-0.0.2.dist-info/RECORD
